certbot_dns_pdns/__init__.py
certbot_dns_pdns/dns_pdns.py
certbot_dns_pdns/py.typed
certbot_dns_pdns-0.1.1.dist-info/LICENSE.txt
certbot_dns_pdns-0.1.1.dist-info/METADATA
certbot_dns_pdns-0.1.1.dist-info/WHEEL
certbot_dns_pdns-0.1.1.dist-info/entry_points.txt
certbot_dns_pdns-0.1.1.dist-info/RECORD
