Metadata-Version: 2.1
Name: certbot-dns-pdns
Version: 0.1.1
Summary: DNS Authenticator for certbot using the PowerDNS API
Home-page: https://github.com/kaechele/certbot-dns-pdns
License: Apache-2.0
Keywords: certbot,powerdns,acme,letsencrypt,dns
Author: Felix Kaechele
Author-email: felix@kaechele.ca
Requires-Python: >=3.11,<4.0
Classifier: Development Status :: 4 - Beta
Classifier: Environment :: Plugins
Classifier: Intended Audience :: System Administrators
Classifier: License :: OSI Approved :: Apache Software License
Classifier: Operating System :: POSIX :: Linux
Classifier: Programming Language :: Python :: 3
Classifier: Programming Language :: Python :: 3.11
Classifier: Programming Language :: Python :: 3.12
Classifier: Topic :: Internet :: WWW/HTTP
Classifier: Topic :: Security
Classifier: Topic :: System :: Installation/Setup
Classifier: Topic :: System :: Networking
Classifier: Topic :: System :: Systems Administration
Classifier: Topic :: Utilities
Requires-Dist: certbot (>=2.7.0)
Requires-Dist: dns-lexicon (>=3.15.0)
Project-URL: Repository, https://github.com/kaechele/certbot-dns-pdns
